algobattle_problems/__init__.py
algobattle_problems/biclique/__init__.py
algobattle_problems/biclique/problem.py
algobattle_problems/biclique/tests.py
algobattle_problems/biclique/generator/main.py
algobattle_problems/biclique/solver/main.py
algobattle_problems/c4subgraphiso/__init__.py
algobattle_problems/c4subgraphiso/problem.py
algobattle_problems/c4subgraphiso/tests.py
algobattle_problems/c4subgraphiso/generator/main.py
algobattle_problems/c4subgraphiso/solver/main.py
algobattle_problems/circlecover/__init__.py
algobattle_problems/circlecover/problem.py
algobattle_problems/circlecover/generator/main.py
algobattle_problems/circlecover/solver/main.py
algobattle_problems/clusterediting/__init__.py
algobattle_problems/clusterediting/problem.py
algobattle_problems/clusterediting/tests.py
algobattle_problems/clusterediting/generator/main.py
algobattle_problems/clusterediting/solver/main.py
algobattle_problems/domset/__init__.py
algobattle_problems/domset/problem.py
algobattle_problems/domset/tests.py
algobattle_problems/domset/generator/main.py
algobattle_problems/domset/solver/main.py
algobattle_problems/hikers/__init__.py
algobattle_problems/hikers/problem.py
algobattle_problems/hikers/tests.py
algobattle_problems/hikers/generator/main.py
algobattle_problems/hikers/solver/main.py
algobattle_problems/longestpathboundedfvs/__init__.py
algobattle_problems/longestpathboundedfvs/problem.py
algobattle_problems/longestpathboundedfvs/generator/main.py
algobattle_problems/longestpathboundedfvs/solver/main.py
algobattle_problems/oscm3/__init__.py
algobattle_problems/oscm3/problem.py
algobattle_problems/oscm3/tests.py
algobattle_problems/oscm3/generator/main.py
algobattle_problems/oscm3/solver/main.py
algobattle_problems/pairsum/__init__.py
algobattle_problems/pairsum/problem.py
algobattle_problems/pairsum/tests.py
algobattle_problems/pairsum/generator/main.py
algobattle_problems/pairsum/generator_random/main.py
algobattle_problems/pairsum/solver/main.py
algobattle_problems-1.0.0.dist-info/LICENSE
algobattle_problems-1.0.0.dist-info/METADATA
algobattle_problems-1.0.0.dist-info/WHEEL
algobattle_problems-1.0.0.dist-info/entry_points.txt
algobattle_problems-1.0.0.dist-info/top_level.txt
algobattle_problems-1.0.0.dist-info/RECORD
