Metadata-Version: 2.1
Name: algobattle-problems
Version: 1.0.0
Author: Imogen Hergeth, Jan Dreier, Henri Lotze
License: MIT
Project-URL: Homepage, https://algobattle.org
Project-URL: Documentation, https://algobattle.org/docs
Project-URL: Repository, https://github.com/Benezivas/algobattle-problems
Requires-Python: >=3.11
License-File: LICENSE
Requires-Dist: algobattle-base ~=4.0.0
Requires-Dist: networkx
